.travis.yml
AUTHORS.rst
CHANGES.rst
CONTRIBUTING.rst
LICENSE
MANIFEST.in
README.rst
RELEASE-NOTES.rst
pytest.ini
setup.py
tox.ini
docs/Makefile
docs/conf.py
docs/index.rst
invenio_client/__init__.py
invenio_client/_compat.py
invenio_client/connector.py
invenio_client/version.py
invenio_client.egg-info/PKG-INFO
invenio_client.egg-info/SOURCES.txt
invenio_client.egg-info/dependency_links.txt
invenio_client.egg-info/requires.txt
invenio_client.egg-info/top_level.txt
invenio_client/contrib/__init__.py
invenio_client/contrib/cds.py
tests/test_connector.py
tests/test_integration.py