Metadata-Version: 1.1
Name: invenio-client
Version: 0.1.0
Summary: Invenio-Client permits to connect to remote Invenio digital library instances.
Home-page: https://github.com/inveniosoftware/invenio-client
Author: Invenio collaboration
Author-email: info@invenio-software.org
License: GPLv2
Platform: UNKNOWN
Classifier: Programming Language :: Python :: 2
Classifier: Programming Language :: Python :: 2.6
Classifier: Programming Language :: Python :: 2.7
Classifier: Programming Language :: Python :: 3
Classifier: Programming Language :: Python :: 3.3
Classifier: Programming Language :: Python :: 3.4
Classifier: Development Status :: 5 - Production/Stable
Classifier: Intended Audience :: Developers
Classifier: License :: OSI Approved :: MIT License
Classifier: Operating System :: OS Independent
Classifier: Topic :: Utilities
